core/__init__.py
core/cm/__init__.py
core/cm/__main__.py
core/cm/commandLine.py
core/consumer/__init__.py
core/consumer/api.py
core/loader/__init__.py
core/loader/image.py
core/loader/parser.py
core/loader/rabbit.py
core/loader/upload.py
core/pipelining/__init__.py
core/pipelining/api.py
core/pipelining/expression.py
core/pipelining/pipeline.py
tests/__init__.py
tests/common.py
tests/context.py
tests/test_consumer.py
tests/test_expression.py
tests/test_image.py
tests/test_parser.py
tests/test_pipeline.py
tests/test_upload.py
ni_core_server-0.1.4.dist-info/LICENSE
ni_core_server-0.1.4.dist-info/METADATA
ni_core_server-0.1.4.dist-info/WHEEL
ni_core_server-0.1.4.dist-info/entry_points.txt
ni_core_server-0.1.4.dist-info/top_level.txt
ni_core_server-0.1.4.dist-info/RECORD
